{
  "NVDA": {
    "metadata": {
      "ticker": "NVDA",
      "spot_price": 202.87,
      "expiration_date": "Historical Aggregated (2026-04-20)",
      "updated_at": "2026-04-21 12:00:58"
    },
    "indicators": {
      "max_pain": 180.0,
      "call_wall": 200.0,
      "put_wall": 180.0,
      "zero_gamma": 169.38
    },
    "gex_chart_data": [
      {
        "strike": 155.0,
        "net_gex": -818715.82
      },
      {
        "strike": 160.0,
        "net_gex": -1816493.15
      },
      {
        "strike": 165.0,
        "net_gex": -1343085.82
      },
      {
        "strike": 170.0,
        "net_gex": -2448908.13
      },
      {
        "strike": 175.0,
        "net_gex": -3533298.04
      },
      {
        "strike": 180.0,
        "net_gex": -3370829.06
      },
      {
        "strike": 185.0,
        "net_gex": 2200976.83
      },
      {
        "strike": 190.0,
        "net_gex": 9604919.41
      },
      {
        "strike": 195.0,
        "net_gex": 17805276.23
      },
      {
        "strike": 200.0,
        "net_gex": 34136686.03
      },
      {
        "strike": 205.0,
        "net_gex": 13035590.31
      },
      {
        "strike": 210.0,
        "net_gex": 21517967.89
      },
      {
        "strike": 215.0,
        "net_gex": 8732044.95
      },
      {
        "strike": 220.0,
        "net_gex": 8187536.46
      },
      {
        "strike": 225.0,
        "net_gex": 1740832.87
      },
      {
        "strike": 230.0,
        "net_gex": 5732953.89
      },
      {
        "strike": 235.0,
        "net_gex": 238600.63
      },
      {
        "strike": 240.0,
        "net_gex": 2734150.37
      },
      {
        "strike": 245.0,
        "net_gex": 756305.04
      },
      {
        "strike": 250.0,
        "net_gex": 1671839.5
      }
    ]
  },
  "AVGO": {
    "metadata": {
      "ticker": "AVGO",
      "spot_price": 399.82,
      "expiration_date": "Historical Aggregated (2026-04-20)",
      "updated_at": "2026-04-21 12:01:20"
    },
    "indicators": {
      "max_pain": 340.0,
      "call_wall": 400.0,
      "put_wall": 370.0,
      "zero_gamma": 333.91
    },
    "gex_chart_data": [
      {
        "strike": 300.0,
        "net_gex": -148983.86
      },
      {
        "strike": 310.0,
        "net_gex": -111432.41
      },
      {
        "strike": 320.0,
        "net_gex": -250927.35
      },
      {
        "strike": 330.0,
        "net_gex": -114485.02
      },
      {
        "strike": 340.0,
        "net_gex": 257519.98
      },
      {
        "strike": 350.0,
        "net_gex": 146148.78
      },
      {
        "strike": 360.0,
        "net_gex": 183606.96
      },
      {
        "strike": 370.0,
        "net_gex": 818351.05
      },
      {
        "strike": 380.0,
        "net_gex": 454515.52
      },
      {
        "strike": 390.0,
        "net_gex": 531284.84
      },
      {
        "strike": 400.0,
        "net_gex": 3022586.41
      },
      {
        "strike": 410.0,
        "net_gex": 1984021.85
      },
      {
        "strike": 420.0,
        "net_gex": 2203409.06
      },
      {
        "strike": 430.0,
        "net_gex": 1409724.1
      },
      {
        "strike": 440.0,
        "net_gex": 1228683.94
      },
      {
        "strike": 450.0,
        "net_gex": 1916085.24
      },
      {
        "strike": 460.0,
        "net_gex": 208729.09
      },
      {
        "strike": 470.0,
        "net_gex": 103077.78
      },
      {
        "strike": 480.0,
        "net_gex": 82182.61
      },
      {
        "strike": 490.0,
        "net_gex": 60251.1
      }
    ]
  },
  "PLTR": {
    "metadata": {
      "ticker": "PLTR",
      "spot_price": 147.11,
      "expiration_date": "Historical Aggregated (2026-04-20)",
      "updated_at": "2026-04-21 12:01:22"
    },
    "indicators": {
      "max_pain": 145.0,
      "call_wall": 150.0,
      "put_wall": 140.0,
      "zero_gamma": 139.62
    },
    "gex_chart_data": [
      {
        "strike": 115.0,
        "net_gex": -304565.89
      },
      {
        "strike": 120.0,
        "net_gex": -825717.26
      },
      {
        "strike": 125.0,
        "net_gex": -1449289.59
      },
      {
        "strike": 130.0,
        "net_gex": -2506869.27
      },
      {
        "strike": 135.0,
        "net_gex": -911173.46
      },
      {
        "strike": 140.0,
        "net_gex": -1499110.93
      },
      {
        "strike": 145.0,
        "net_gex": -522434.36
      },
      {
        "strike": 150.0,
        "net_gex": 6908308.24
      },
      {
        "strike": 155.0,
        "net_gex": 2486893.38
      },
      {
        "strike": 160.0,
        "net_gex": 2007804.89
      },
      {
        "strike": 165.0,
        "net_gex": 1237401.84
      },
      {
        "strike": 170.0,
        "net_gex": 919736.91
      },
      {
        "strike": 175.0,
        "net_gex": 669493.21
      },
      {
        "strike": 180.0,
        "net_gex": 724233.51
      }
    ]
  },
  "COIN": {
    "metadata": {
      "ticker": "COIN",
      "spot_price": 213.77,
      "expiration_date": "Historical Aggregated (2026-04-20)",
      "updated_at": "2026-04-21 12:01:24"
    },
    "indicators": {
      "max_pain": 190.0,
      "call_wall": 220.0,
      "put_wall": 200.0,
      "zero_gamma": 169.77
    },
    "gex_chart_data": [
      {
        "strike": 165.0,
        "net_gex": -22736.69
      },
      {
        "strike": 170.0,
        "net_gex": -98860.16
      },
      {
        "strike": 175.0,
        "net_gex": 88148.0
      },
      {
        "strike": 180.0,
        "net_gex": -79834.35
      },
      {
        "strike": 185.0,
        "net_gex": -227328.2
      },
      {
        "strike": 190.0,
        "net_gex": 1417361.51
      },
      {
        "strike": 195.0,
        "net_gex": -417275.57
      },
      {
        "strike": 200.0,
        "net_gex": 86855.9
      },
      {
        "strike": 210.0,
        "net_gex": 1167501.32
      },
      {
        "strike": 220.0,
        "net_gex": 2016543.16
      },
      {
        "strike": 230.0,
        "net_gex": 277319.87
      },
      {
        "strike": 240.0,
        "net_gex": -3562.89
      },
      {
        "strike": 250.0,
        "net_gex": 916841.83
      },
      {
        "strike": 260.0,
        "net_gex": 141748.21
      }
    ]
  },
  "SPY": {
    "metadata": {
      "ticker": "SPY",
      "spot_price": 711.63,
      "expiration_date": "Historical Aggregated (2026-04-20)",
      "updated_at": "2026-04-21 12:00:50"
    },
    "indicators": {
      "max_pain": 677.0,
      "call_wall": 723.0,
      "put_wall": 660.0,
      "zero_gamma": 708.09
    },
    "gex_chart_data": [
      {
        "strike": 535.0,
        "net_gex": -815.16
      },
      {
        "strike": 540.0,
        "net_gex": -1567.58
      },
      {
        "strike": 545.0,
        "net_gex": -903.12
      },
      {
        "strike": 550.0,
        "net_gex": -51281.28
      },
      {
        "strike": 555.0,
        "net_gex": -5731.79
      },
      {
        "strike": 560.0,
        "net_gex": -7973.52
      },
      {
        "strike": 565.0,
        "net_gex": -31911.37
      },
      {
        "strike": 570.0,
        "net_gex": -63790.91
      },
      {
        "strike": 575.0,
        "net_gex": -95718.69
      },
      {
        "strike": 580.0,
        "net_gex": -216409.3
      },
      {
        "strike": 585.0,
        "net_gex": -294775.21
      },
      {
        "strike": 590.0,
        "net_gex": -118267.12
      },
      {
        "strike": 591.0,
        "net_gex": -145297.61
      },
      {
        "strike": 592.0,
        "net_gex": -28508.83
      },
      {
        "strike": 593.0,
        "net_gex": -16671.52
      },
      {
        "strike": 594.0,
        "net_gex": -7653.4
      },
      {
        "strike": 595.0,
        "net_gex": -73028.98
      },
      {
        "strike": 596.0,
        "net_gex": -20965.87
      },
      {
        "strike": 597.0,
        "net_gex": -26573.26
      },
      {
        "strike": 598.0,
        "net_gex": -13093.07
      },
      {
        "strike": 599.0,
        "net_gex": -13981.85
      },
      {
        "strike": 600.0,
        "net_gex": -995775.62
      },
      {
        "strike": 601.0,
        "net_gex": -33287.85
      },
      {
        "strike": 602.0,
        "net_gex": -38061.62
      },
      {
        "strike": 603.0,
        "net_gex": -28646.84
      },
      {
        "strike": 604.0,
        "net_gex": -147263.86
      },
      {
        "strike": 605.0,
        "net_gex": -167198.88
      },
      {
        "strike": 606.0,
        "net_gex": -21025.64
      },
      {
        "strike": 607.0,
        "net_gex": -24435.01
      },
      {
        "strike": 608.0,
        "net_gex": -67595.83
      },
      {
        "strike": 609.0,
        "net_gex": -62294.38
      },
      {
        "strike": 610.0,
        "net_gex": -578003.41
      },
      {
        "strike": 611.0,
        "net_gex": -41228.11
      },
      {
        "strike": 612.0,
        "net_gex": -46378.05
      },
      {
        "strike": 613.0,
        "net_gex": -24570.71
      },
      {
        "strike": 614.0,
        "net_gex": -243770.94
      },
      {
        "strike": 615.0,
        "net_gex": -771010.01
      },
      {
        "strike": 616.0,
        "net_gex": -56824.39
      },
      {
        "strike": 617.0,
        "net_gex": -72093.68
      },
      {
        "strike": 618.0,
        "net_gex": -47394.9
      },
      {
        "strike": 619.0,
        "net_gex": -115364.45
      },
      {
        "strike": 620.0,
        "net_gex": -1326061.8
      },
      {
        "strike": 621.0,
        "net_gex": -111595.04
      },
      {
        "strike": 622.0,
        "net_gex": -93739.49
      },
      {
        "strike": 623.0,
        "net_gex": -40616.2
      },
      {
        "strike": 624.0,
        "net_gex": -191376.34
      },
      {
        "strike": 625.0,
        "net_gex": -744904.27
      },
      {
        "strike": 626.0,
        "net_gex": -52117.05
      },
      {
        "strike": 627.0,
        "net_gex": -97161.12
      },
      {
        "strike": 628.0,
        "net_gex": -62602.07
      },
      {
        "strike": 629.0,
        "net_gex": -77488.53
      },
      {
        "strike": 630.0,
        "net_gex": -3316886.73
      },
      {
        "strike": 631.0,
        "net_gex": -103857.04
      },
      {
        "strike": 632.0,
        "net_gex": -71420.46
      },
      {
        "strike": 633.0,
        "net_gex": -132085.04
      },
      {
        "strike": 634.0,
        "net_gex": -14020.27
      },
      {
        "strike": 635.0,
        "net_gex": -3101069.79
      },
      {
        "strike": 636.0,
        "net_gex": 132162.77
      },
      {
        "strike": 637.0,
        "net_gex": -688771.49
      },
      {
        "strike": 638.0,
        "net_gex": -167217.1
      },
      {
        "strike": 639.0,
        "net_gex": -262160.32
      },
      {
        "strike": 640.0,
        "net_gex": -2984681.13
      },
      {
        "strike": 641.0,
        "net_gex": 18155.77
      },
      {
        "strike": 642.0,
        "net_gex": -77639.67
      },
      {
        "strike": 643.0,
        "net_gex": -151258.77
      },
      {
        "strike": 644.0,
        "net_gex": -404553.33
      },
      {
        "strike": 645.0,
        "net_gex": -2361744.74
      },
      {
        "strike": 646.0,
        "net_gex": -139675.58
      },
      {
        "strike": 647.0,
        "net_gex": -1098527.8
      },
      {
        "strike": 648.0,
        "net_gex": -138844.7
      },
      {
        "strike": 649.0,
        "net_gex": -77723.75
      },
      {
        "strike": 650.0,
        "net_gex": -3139470.5
      },
      {
        "strike": 651.0,
        "net_gex": -83747.53
      },
      {
        "strike": 652.0,
        "net_gex": -772.03
      },
      {
        "strike": 653.0,
        "net_gex": -66858.05
      },
      {
        "strike": 654.0,
        "net_gex": 25835.49
      },
      {
        "strike": 655.0,
        "net_gex": -9569100.38
      },
      {
        "strike": 656.0,
        "net_gex": -1092972.03
      },
      {
        "strike": 657.0,
        "net_gex": -40167.75
      },
      {
        "strike": 658.0,
        "net_gex": -641367.11
      },
      {
        "strike": 659.0,
        "net_gex": 169725.81
      },
      {
        "strike": 660.0,
        "net_gex": -17613124.48
      },
      {
        "strike": 661.0,
        "net_gex": -73326.37
      },
      {
        "strike": 662.0,
        "net_gex": 24697.67
      },
      {
        "strike": 663.0,
        "net_gex": -247721.03
      },
      {
        "strike": 664.0,
        "net_gex": -365236.67
      },
      {
        "strike": 665.0,
        "net_gex": -5127174.51
      },
      {
        "strike": 666.0,
        "net_gex": -260907.78
      },
      {
        "strike": 667.0,
        "net_gex": 440774.78
      },
      {
        "strike": 668.0,
        "net_gex": -411898.87
      },
      {
        "strike": 669.0,
        "net_gex": -274187.05
      },
      {
        "strike": 670.0,
        "net_gex": -6711979.71
      },
      {
        "strike": 671.0,
        "net_gex": 40198.63
      },
      {
        "strike": 672.0,
        "net_gex": 15349.18
      },
      {
        "strike": 673.0,
        "net_gex": 1378604.15
      },
      {
        "strike": 674.0,
        "net_gex": 116756.62
      },
      {
        "strike": 675.0,
        "net_gex": -5575515.42
      },
      {
        "strike": 676.0,
        "net_gex": -76432.33
      },
      {
        "strike": 677.0,
        "net_gex": -123585.21
      },
      {
        "strike": 678.0,
        "net_gex": 47141.97
      },
      {
        "strike": 679.0,
        "net_gex": -5760.37
      },
      {
        "strike": 680.0,
        "net_gex": -541349.67
      },
      {
        "strike": 681.0,
        "net_gex": 537994.2
      },
      {
        "strike": 682.0,
        "net_gex": -196417.68
      },
      {
        "strike": 683.0,
        "net_gex": -131806.1
      },
      {
        "strike": 684.0,
        "net_gex": 750025.34
      },
      {
        "strike": 685.0,
        "net_gex": -4378193.65
      },
      {
        "strike": 686.0,
        "net_gex": 889072.32
      },
      {
        "strike": 687.0,
        "net_gex": 768854.69
      },
      {
        "strike": 688.0,
        "net_gex": -326187.56
      },
      {
        "strike": 689.0,
        "net_gex": 329508.67
      },
      {
        "strike": 690.0,
        "net_gex": -1964714.81
      },
      {
        "strike": 691.0,
        "net_gex": 256560.07
      },
      {
        "strike": 692.0,
        "net_gex": 187008.78
      },
      {
        "strike": 693.0,
        "net_gex": 380068.41
      },
      {
        "strike": 694.0,
        "net_gex": 153188.37
      },
      {
        "strike": 695.0,
        "net_gex": 2532277.52
      },
      {
        "strike": 696.0,
        "net_gex": 29787.5
      },
      {
        "strike": 697.0,
        "net_gex": 372150.38
      },
      {
        "strike": 698.0,
        "net_gex": 780566.66
      },
      {
        "strike": 699.0,
        "net_gex": 215961.07
      },
      {
        "strike": 700.0,
        "net_gex": 390847.76
      },
      {
        "strike": 701.0,
        "net_gex": 665428.12
      },
      {
        "strike": 702.0,
        "net_gex": 668761.86
      },
      {
        "strike": 703.0,
        "net_gex": 297400.67
      },
      {
        "strike": 704.0,
        "net_gex": 558008.38
      },
      {
        "strike": 705.0,
        "net_gex": 2367000.88
      },
      {
        "strike": 706.0,
        "net_gex": 55745.02
      },
      {
        "strike": 707.0,
        "net_gex": -789507.61
      },
      {
        "strike": 708.0,
        "net_gex": 204385.48
      },
      {
        "strike": 709.0,
        "net_gex": 345349.35
      },
      {
        "strike": 710.0,
        "net_gex": 5431714.37
      },
      {
        "strike": 711.0,
        "net_gex": 486823.9
      },
      {
        "strike": 712.0,
        "net_gex": 339584.41
      },
      {
        "strike": 713.0,
        "net_gex": 477961.33
      },
      {
        "strike": 714.0,
        "net_gex": 640709.03
      },
      {
        "strike": 715.0,
        "net_gex": 3662392.29
      },
      {
        "strike": 716.0,
        "net_gex": 601406.88
      },
      {
        "strike": 717.0,
        "net_gex": 1242167.37
      },
      {
        "strike": 718.0,
        "net_gex": 603512.12
      },
      {
        "strike": 719.0,
        "net_gex": 550079.87
      },
      {
        "strike": 720.0,
        "net_gex": 2247962.95
      },
      {
        "strike": 721.0,
        "net_gex": 806137.06
      },
      {
        "strike": 722.0,
        "net_gex": 423092.71
      },
      {
        "strike": 723.0,
        "net_gex": 10147560.82
      },
      {
        "strike": 724.0,
        "net_gex": 450923.28
      },
      {
        "strike": 725.0,
        "net_gex": 4693057.41
      },
      {
        "strike": 726.0,
        "net_gex": 426095.8
      },
      {
        "strike": 727.0,
        "net_gex": 1149571.55
      },
      {
        "strike": 728.0,
        "net_gex": 739439.2
      },
      {
        "strike": 729.0,
        "net_gex": 700846.94
      },
      {
        "strike": 730.0,
        "net_gex": 969818.64
      },
      {
        "strike": 731.0,
        "net_gex": 1360159.45
      },
      {
        "strike": 732.0,
        "net_gex": 646501.83
      },
      {
        "strike": 733.0,
        "net_gex": 963951.4
      },
      {
        "strike": 734.0,
        "net_gex": 543402.5
      },
      {
        "strike": 735.0,
        "net_gex": 2673374.49
      },
      {
        "strike": 736.0,
        "net_gex": 521999.06
      },
      {
        "strike": 737.0,
        "net_gex": 714563.84
      },
      {
        "strike": 738.0,
        "net_gex": 524269.7
      },
      {
        "strike": 739.0,
        "net_gex": 748977.44
      },
      {
        "strike": 740.0,
        "net_gex": 2811962.27
      },
      {
        "strike": 741.0,
        "net_gex": 272935.38
      },
      {
        "strike": 742.0,
        "net_gex": 338641.5
      },
      {
        "strike": 743.0,
        "net_gex": 3029047.46
      },
      {
        "strike": 744.0,
        "net_gex": 602181.37
      },
      {
        "strike": 745.0,
        "net_gex": 2152149.11
      },
      {
        "strike": 746.0,
        "net_gex": 285394.18
      },
      {
        "strike": 747.0,
        "net_gex": 445468.03
      },
      {
        "strike": 748.0,
        "net_gex": 3213079.02
      },
      {
        "strike": 749.0,
        "net_gex": 910768.35
      },
      {
        "strike": 750.0,
        "net_gex": 2282478.13
      },
      {
        "strike": 755.0,
        "net_gex": 558121.98
      },
      {
        "strike": 760.0,
        "net_gex": 468693.02
      },
      {
        "strike": 765.0,
        "net_gex": 859117.75
      },
      {
        "strike": 770.0,
        "net_gex": 846958.63
      },
      {
        "strike": 775.0,
        "net_gex": 521527.86
      },
      {
        "strike": 780.0,
        "net_gex": 582970.69
      },
      {
        "strike": 785.0,
        "net_gex": 145286.96
      },
      {
        "strike": 790.0,
        "net_gex": 981102.48
      },
      {
        "strike": 795.0,
        "net_gex": 1703940.26
      },
      {
        "strike": 800.0,
        "net_gex": 2370521.09
      },
      {
        "strike": 805.0,
        "net_gex": 157233.33
      },
      {
        "strike": 810.0,
        "net_gex": 671722.35
      },
      {
        "strike": 815.0,
        "net_gex": 669367.17
      },
      {
        "strike": 820.0,
        "net_gex": 528669.03
      },
      {
        "strike": 825.0,
        "net_gex": 140018.31
      },
      {
        "strike": 830.0,
        "net_gex": 809277.05
      },
      {
        "strike": 835.0,
        "net_gex": 262023.4
      },
      {
        "strike": 840.0,
        "net_gex": 29863.16
      },
      {
        "strike": 845.0,
        "net_gex": 5086.26
      },
      {
        "strike": 850.0,
        "net_gex": 14458.13
      },
      {
        "strike": 855.0,
        "net_gex": 11253.72
      },
      {
        "strike": 860.0,
        "net_gex": 10724.8
      },
      {
        "strike": 865.0,
        "net_gex": 18705.81
      },
      {
        "strike": 870.0,
        "net_gex": 810.83
      },
      {
        "strike": 875.0,
        "net_gex": 163.81
      },
      {
        "strike": 880.0,
        "net_gex": 225.79
      },
      {
        "strike": 885.0,
        "net_gex": 61.99
      }
    ]
  },
  "QQQ": {
    "metadata": {
      "ticker": "QQQ",
      "spot_price": 649.98,
      "expiration_date": "Historical Aggregated (2026-04-20)",
      "updated_at": "2026-04-21 12:00:53"
    },
    "indicators": {
      "max_pain": 610.0,
      "call_wall": 665.0,
      "put_wall": 585.0,
      "zero_gamma": 630.12
    },
    "gex_chart_data": [
      {
        "strike": 490.0,
        "net_gex": -5066.76
      },
      {
        "strike": 495.0,
        "net_gex": -677.15
      },
      {
        "strike": 500.0,
        "net_gex": -5307.33
      },
      {
        "strike": 505.0,
        "net_gex": -1874.54
      },
      {
        "strike": 510.0,
        "net_gex": -17731.96
      },
      {
        "strike": 515.0,
        "net_gex": -10745.2
      },
      {
        "strike": 520.0,
        "net_gex": -25569.77
      },
      {
        "strike": 525.0,
        "net_gex": -68003.82
      },
      {
        "strike": 530.0,
        "net_gex": -22097.59
      },
      {
        "strike": 535.0,
        "net_gex": -152997.15
      },
      {
        "strike": 540.0,
        "net_gex": -150913.86
      },
      {
        "strike": 545.0,
        "net_gex": -449709.84
      },
      {
        "strike": 550.0,
        "net_gex": -718122.4
      },
      {
        "strike": 555.0,
        "net_gex": -321611.65
      },
      {
        "strike": 560.0,
        "net_gex": -676015.96
      },
      {
        "strike": 561.0,
        "net_gex": -29687.05
      },
      {
        "strike": 562.0,
        "net_gex": -22134.89
      },
      {
        "strike": 563.0,
        "net_gex": -13845.24
      },
      {
        "strike": 564.0,
        "net_gex": 13269.58
      },
      {
        "strike": 565.0,
        "net_gex": -114157.9
      },
      {
        "strike": 566.0,
        "net_gex": -14120.84
      },
      {
        "strike": 567.0,
        "net_gex": -53917.99
      },
      {
        "strike": 568.0,
        "net_gex": -10521.72
      },
      {
        "strike": 569.0,
        "net_gex": -13044.77
      },
      {
        "strike": 570.0,
        "net_gex": -635068.92
      },
      {
        "strike": 571.0,
        "net_gex": -12776.24
      },
      {
        "strike": 572.0,
        "net_gex": -2727.76
      },
      {
        "strike": 573.0,
        "net_gex": 21231.87
      },
      {
        "strike": 574.0,
        "net_gex": -76478.12
      },
      {
        "strike": 575.0,
        "net_gex": -913471.43
      },
      {
        "strike": 576.0,
        "net_gex": -299184.24
      },
      {
        "strike": 577.0,
        "net_gex": 16329.27
      },
      {
        "strike": 578.0,
        "net_gex": -108467.38
      },
      {
        "strike": 579.0,
        "net_gex": -38776.45
      },
      {
        "strike": 580.0,
        "net_gex": -854502.89
      },
      {
        "strike": 581.0,
        "net_gex": -269752.14
      },
      {
        "strike": 582.0,
        "net_gex": -28401.24
      },
      {
        "strike": 583.0,
        "net_gex": -100249.37
      },
      {
        "strike": 584.0,
        "net_gex": -43309.06
      },
      {
        "strike": 585.0,
        "net_gex": -2720285.13
      },
      {
        "strike": 586.0,
        "net_gex": -6148.97
      },
      {
        "strike": 587.0,
        "net_gex": 0.0
      },
      {
        "strike": 588.0,
        "net_gex": 5047.7
      },
      {
        "strike": 589.0,
        "net_gex": -36788.64
      },
      {
        "strike": 590.0,
        "net_gex": -109493.55
      },
      {
        "strike": 591.0,
        "net_gex": 7777.47
      },
      {
        "strike": 592.0,
        "net_gex": 15275.19
      },
      {
        "strike": 593.0,
        "net_gex": 12065.26
      },
      {
        "strike": 594.0,
        "net_gex": 77762.53
      },
      {
        "strike": 595.0,
        "net_gex": 1811026.53
      },
      {
        "strike": 596.0,
        "net_gex": -1453083.65
      },
      {
        "strike": 597.0,
        "net_gex": 71263.51
      },
      {
        "strike": 598.0,
        "net_gex": 61783.26
      },
      {
        "strike": 599.0,
        "net_gex": -33304.4
      },
      {
        "strike": 600.0,
        "net_gex": -239695.05
      },
      {
        "strike": 601.0,
        "net_gex": -1120586.58
      },
      {
        "strike": 602.0,
        "net_gex": 55389.56
      },
      {
        "strike": 603.0,
        "net_gex": 25085.09
      },
      {
        "strike": 604.0,
        "net_gex": -889458.73
      },
      {
        "strike": 605.0,
        "net_gex": -433397.36
      },
      {
        "strike": 606.0,
        "net_gex": 41973.76
      },
      {
        "strike": 607.0,
        "net_gex": -1681003.9
      },
      {
        "strike": 608.0,
        "net_gex": -307114.02
      },
      {
        "strike": 609.0,
        "net_gex": 229850.69
      },
      {
        "strike": 610.0,
        "net_gex": 43515.58
      },
      {
        "strike": 611.0,
        "net_gex": 15717.25
      },
      {
        "strike": 612.0,
        "net_gex": 87950.67
      },
      {
        "strike": 613.0,
        "net_gex": -835279.49
      },
      {
        "strike": 614.0,
        "net_gex": -32308.9
      },
      {
        "strike": 615.0,
        "net_gex": -790507.36
      },
      {
        "strike": 616.0,
        "net_gex": 19382.09
      },
      {
        "strike": 617.0,
        "net_gex": 202649.79
      },
      {
        "strike": 618.0,
        "net_gex": 35533.81
      },
      {
        "strike": 619.0,
        "net_gex": 31178.91
      },
      {
        "strike": 620.0,
        "net_gex": 1575022.57
      },
      {
        "strike": 621.0,
        "net_gex": -99408.83
      },
      {
        "strike": 622.0,
        "net_gex": 251923.45
      },
      {
        "strike": 623.0,
        "net_gex": 150553.76
      },
      {
        "strike": 624.0,
        "net_gex": 279673.57
      },
      {
        "strike": 625.0,
        "net_gex": -752634.56
      },
      {
        "strike": 626.0,
        "net_gex": 118294.35
      },
      {
        "strike": 627.0,
        "net_gex": -2398635.64
      },
      {
        "strike": 628.0,
        "net_gex": 42360.47
      },
      {
        "strike": 629.0,
        "net_gex": 223883.01
      },
      {
        "strike": 630.0,
        "net_gex": -31232.26
      },
      {
        "strike": 631.0,
        "net_gex": -79703.56
      },
      {
        "strike": 632.0,
        "net_gex": 70566.41
      },
      {
        "strike": 633.0,
        "net_gex": -54647.32
      },
      {
        "strike": 634.0,
        "net_gex": 16614.51
      },
      {
        "strike": 635.0,
        "net_gex": 861115.44
      },
      {
        "strike": 636.0,
        "net_gex": 123717.04
      },
      {
        "strike": 637.0,
        "net_gex": 145825.32
      },
      {
        "strike": 638.0,
        "net_gex": 214442.73
      },
      {
        "strike": 639.0,
        "net_gex": -2940.53
      },
      {
        "strike": 640.0,
        "net_gex": -912333.99
      },
      {
        "strike": 641.0,
        "net_gex": 431611.51
      },
      {
        "strike": 642.0,
        "net_gex": 72580.26
      },
      {
        "strike": 643.0,
        "net_gex": 162704.14
      },
      {
        "strike": 644.0,
        "net_gex": -19032.99
      },
      {
        "strike": 645.0,
        "net_gex": 140183.84
      },
      {
        "strike": 646.0,
        "net_gex": 1087286.88
      },
      {
        "strike": 647.0,
        "net_gex": 185347.69
      },
      {
        "strike": 648.0,
        "net_gex": 161424.88
      },
      {
        "strike": 649.0,
        "net_gex": 133298.48
      },
      {
        "strike": 650.0,
        "net_gex": 1227007.56
      },
      {
        "strike": 651.0,
        "net_gex": 219396.02
      },
      {
        "strike": 652.0,
        "net_gex": 182400.85
      },
      {
        "strike": 653.0,
        "net_gex": 213404.32
      },
      {
        "strike": 654.0,
        "net_gex": 197079.76
      },
      {
        "strike": 655.0,
        "net_gex": 661880.98
      },
      {
        "strike": 656.0,
        "net_gex": 243372.74
      },
      {
        "strike": 657.0,
        "net_gex": 461226.87
      },
      {
        "strike": 658.0,
        "net_gex": 91975.26
      },
      {
        "strike": 659.0,
        "net_gex": 125052.76
      },
      {
        "strike": 660.0,
        "net_gex": 2499147.95
      },
      {
        "strike": 661.0,
        "net_gex": 268787.58
      },
      {
        "strike": 662.0,
        "net_gex": 60477.25
      },
      {
        "strike": 663.0,
        "net_gex": 1437663.35
      },
      {
        "strike": 664.0,
        "net_gex": 52076.97
      },
      {
        "strike": 665.0,
        "net_gex": 3905413.33
      },
      {
        "strike": 666.0,
        "net_gex": 266856.59
      },
      {
        "strike": 667.0,
        "net_gex": 772524.45
      },
      {
        "strike": 668.0,
        "net_gex": 70509.12
      },
      {
        "strike": 669.0,
        "net_gex": 633310.25
      },
      {
        "strike": 670.0,
        "net_gex": 1125724.01
      },
      {
        "strike": 671.0,
        "net_gex": 1042494.74
      },
      {
        "strike": 672.0,
        "net_gex": 130365.72
      },
      {
        "strike": 673.0,
        "net_gex": 1115416.49
      },
      {
        "strike": 674.0,
        "net_gex": 319486.17
      },
      {
        "strike": 675.0,
        "net_gex": 3388821.47
      },
      {
        "strike": 680.0,
        "net_gex": 3089802.07
      },
      {
        "strike": 685.0,
        "net_gex": 434446.86
      },
      {
        "strike": 690.0,
        "net_gex": 280153.06
      },
      {
        "strike": 695.0,
        "net_gex": 165514.05
      },
      {
        "strike": 700.0,
        "net_gex": 715499.15
      },
      {
        "strike": 705.0,
        "net_gex": 177694.15
      },
      {
        "strike": 710.0,
        "net_gex": 162273.45
      },
      {
        "strike": 715.0,
        "net_gex": 25335.8
      },
      {
        "strike": 720.0,
        "net_gex": 18116.8
      },
      {
        "strike": 725.0,
        "net_gex": 1243.23
      },
      {
        "strike": 730.0,
        "net_gex": 124832.02
      },
      {
        "strike": 735.0,
        "net_gex": 24231.99
      }
    ]
  },
  "IWM": {
    "metadata": {
      "ticker": "IWM",
      "spot_price": 278.41,
      "expiration_date": "Historical Aggregated (2026-04-20)",
      "updated_at": "2026-04-21 12:00:55"
    },
    "indicators": {
      "max_pain": 263.0,
      "call_wall": 280.0,
      "put_wall": 250.0,
      "zero_gamma": 304.4
    },
    "gex_chart_data": [
      {
        "strike": 210.0,
        "net_gex": -462003.52
      },
      {
        "strike": 215.0,
        "net_gex": -794168.38
      },
      {
        "strike": 220.0,
        "net_gex": -1983669.28
      },
      {
        "strike": 225.0,
        "net_gex": -3130747.86
      },
      {
        "strike": 226.0,
        "net_gex": -391647.05
      },
      {
        "strike": 227.0,
        "net_gex": -145383.28
      },
      {
        "strike": 228.0,
        "net_gex": -492853.87
      },
      {
        "strike": 229.0,
        "net_gex": -369392.2
      },
      {
        "strike": 230.0,
        "net_gex": -3865787.5
      },
      {
        "strike": 231.0,
        "net_gex": -221655.9
      },
      {
        "strike": 232.0,
        "net_gex": -591228.99
      },
      {
        "strike": 233.0,
        "net_gex": -146188.02
      },
      {
        "strike": 234.0,
        "net_gex": -73152.61
      },
      {
        "strike": 235.0,
        "net_gex": -3827085.44
      },
      {
        "strike": 236.0,
        "net_gex": -191030.84
      },
      {
        "strike": 237.0,
        "net_gex": -485312.45
      },
      {
        "strike": 238.0,
        "net_gex": -1350894.07
      },
      {
        "strike": 239.0,
        "net_gex": -1215942.7
      },
      {
        "strike": 240.0,
        "net_gex": -9101008.63
      },
      {
        "strike": 241.0,
        "net_gex": -2592452.29
      },
      {
        "strike": 242.0,
        "net_gex": -663095.31
      },
      {
        "strike": 243.0,
        "net_gex": -378393.28
      },
      {
        "strike": 244.0,
        "net_gex": -404051.74
      },
      {
        "strike": 245.0,
        "net_gex": -8103962.05
      },
      {
        "strike": 246.0,
        "net_gex": -569139.86
      },
      {
        "strike": 247.0,
        "net_gex": -1464617.43
      },
      {
        "strike": 248.0,
        "net_gex": -1787946.78
      },
      {
        "strike": 249.0,
        "net_gex": -4131313.1
      },
      {
        "strike": 250.0,
        "net_gex": -23610580.07
      },
      {
        "strike": 251.0,
        "net_gex": -4651183.61
      },
      {
        "strike": 252.0,
        "net_gex": -4970491.36
      },
      {
        "strike": 253.0,
        "net_gex": -138122.93
      },
      {
        "strike": 254.0,
        "net_gex": -6172906.68
      },
      {
        "strike": 255.0,
        "net_gex": -9945168.32
      },
      {
        "strike": 256.0,
        "net_gex": -4651567.56
      },
      {
        "strike": 257.0,
        "net_gex": -8398698.21
      },
      {
        "strike": 258.0,
        "net_gex": -652088.0
      },
      {
        "strike": 259.0,
        "net_gex": -211081.08
      },
      {
        "strike": 260.0,
        "net_gex": -11214885.37
      },
      {
        "strike": 261.0,
        "net_gex": -7188349.55
      },
      {
        "strike": 262.0,
        "net_gex": -2358818.13
      },
      {
        "strike": 263.0,
        "net_gex": -10572145.45
      },
      {
        "strike": 264.0,
        "net_gex": -786233.52
      },
      {
        "strike": 265.0,
        "net_gex": -2838500.21
      },
      {
        "strike": 266.0,
        "net_gex": 7342.82
      },
      {
        "strike": 267.0,
        "net_gex": 5553271.91
      },
      {
        "strike": 268.0,
        "net_gex": 685595.44
      },
      {
        "strike": 269.0,
        "net_gex": -107889.69
      },
      {
        "strike": 270.0,
        "net_gex": 761773.16
      },
      {
        "strike": 271.0,
        "net_gex": 1006926.06
      },
      {
        "strike": 272.0,
        "net_gex": 1242718.99
      },
      {
        "strike": 273.0,
        "net_gex": 2809248.56
      },
      {
        "strike": 274.0,
        "net_gex": 9970863.86
      },
      {
        "strike": 275.0,
        "net_gex": 9151059.21
      },
      {
        "strike": 276.0,
        "net_gex": 1370197.68
      },
      {
        "strike": 277.0,
        "net_gex": 338099.26
      },
      {
        "strike": 278.0,
        "net_gex": 1531275.48
      },
      {
        "strike": 279.0,
        "net_gex": 616217.57
      },
      {
        "strike": 280.0,
        "net_gex": 16465922.7
      },
      {
        "strike": 281.0,
        "net_gex": 3176056.06
      },
      {
        "strike": 282.0,
        "net_gex": 619442.84
      },
      {
        "strike": 283.0,
        "net_gex": 3242700.4
      },
      {
        "strike": 284.0,
        "net_gex": 392639.73
      },
      {
        "strike": 285.0,
        "net_gex": 7899113.57
      },
      {
        "strike": 286.0,
        "net_gex": 608815.79
      },
      {
        "strike": 287.0,
        "net_gex": 368771.55
      },
      {
        "strike": 288.0,
        "net_gex": 340783.17
      },
      {
        "strike": 289.0,
        "net_gex": 414852.43
      },
      {
        "strike": 290.0,
        "net_gex": 3401547.59
      },
      {
        "strike": 295.0,
        "net_gex": 608587.99
      },
      {
        "strike": 300.0,
        "net_gex": 1805426.28
      },
      {
        "strike": 305.0,
        "net_gex": 392690.75
      },
      {
        "strike": 310.0,
        "net_gex": 641553.88
      },
      {
        "strike": 315.0,
        "net_gex": 219588.57
      },
      {
        "strike": 320.0,
        "net_gex": 293658.72
      },
      {
        "strike": 325.0,
        "net_gex": 101619.16
      },
      {
        "strike": 330.0,
        "net_gex": 162158.04
      },
      {
        "strike": 335.0,
        "net_gex": 142565.15
      },
      {
        "strike": 340.0,
        "net_gex": 302762.4
      },
      {
        "strike": 345.0,
        "net_gex": 46032.56
      }
    ]
  },
  "TSLA": {
    "metadata": {
      "ticker": "TSLA",
      "spot_price": 396.01,
      "expiration_date": "Historical Aggregated (2026-04-20)",
      "updated_at": "2026-04-21 12:01:00"
    },
    "indicators": {
      "max_pain": 380.0,
      "call_wall": 410.0,
      "put_wall": 380.0,
      "zero_gamma": 366.99
    },
    "gex_chart_data": [
      {
        "strike": 300.0,
        "net_gex": -182479.58
      },
      {
        "strike": 305.0,
        "net_gex": -33649.63
      },
      {
        "strike": 310.0,
        "net_gex": -152470.16
      },
      {
        "strike": 315.0,
        "net_gex": -164024.29
      },
      {
        "strike": 320.0,
        "net_gex": -717711.06
      },
      {
        "strike": 325.0,
        "net_gex": -280605.17
      },
      {
        "strike": 330.0,
        "net_gex": -795669.63
      },
      {
        "strike": 335.0,
        "net_gex": -289836.99
      },
      {
        "strike": 340.0,
        "net_gex": -397622.06
      },
      {
        "strike": 345.0,
        "net_gex": -421641.98
      },
      {
        "strike": 350.0,
        "net_gex": -1962041.01
      },
      {
        "strike": 355.0,
        "net_gex": -74603.7
      },
      {
        "strike": 360.0,
        "net_gex": -1007600.34
      },
      {
        "strike": 365.0,
        "net_gex": -127922.52
      },
      {
        "strike": 370.0,
        "net_gex": -1100308.98
      },
      {
        "strike": 375.0,
        "net_gex": 231161.33
      },
      {
        "strike": 380.0,
        "net_gex": -2410474.08
      },
      {
        "strike": 385.0,
        "net_gex": -144073.35
      },
      {
        "strike": 390.0,
        "net_gex": 32608.96
      },
      {
        "strike": 395.0,
        "net_gex": 846070.14
      },
      {
        "strike": 400.0,
        "net_gex": 1260474.73
      },
      {
        "strike": 405.0,
        "net_gex": 3925033.53
      },
      {
        "strike": 410.0,
        "net_gex": 4461193.03
      },
      {
        "strike": 415.0,
        "net_gex": 430159.61
      },
      {
        "strike": 420.0,
        "net_gex": 1745406.26
      },
      {
        "strike": 425.0,
        "net_gex": 904524.94
      },
      {
        "strike": 430.0,
        "net_gex": 1018263.47
      },
      {
        "strike": 435.0,
        "net_gex": 1601363.61
      },
      {
        "strike": 440.0,
        "net_gex": 1822844.41
      },
      {
        "strike": 445.0,
        "net_gex": 715086.0
      },
      {
        "strike": 450.0,
        "net_gex": 2906519.83
      },
      {
        "strike": 455.0,
        "net_gex": 297338.51
      },
      {
        "strike": 460.0,
        "net_gex": 923340.26
      },
      {
        "strike": 465.0,
        "net_gex": 298574.1
      },
      {
        "strike": 470.0,
        "net_gex": 906875.27
      },
      {
        "strike": 475.0,
        "net_gex": 183931.71
      },
      {
        "strike": 480.0,
        "net_gex": 316341.69
      },
      {
        "strike": 485.0,
        "net_gex": 69264.21
      },
      {
        "strike": 490.0,
        "net_gex": 325846.72
      },
      {
        "strike": 495.0,
        "net_gex": 47731.98
      }
    ]
  },
  "AAPL": {
    "metadata": {
      "ticker": "AAPL",
      "spot_price": 272.29,
      "expiration_date": "Historical Aggregated (2026-04-20)",
      "updated_at": "2026-04-21 12:01:02"
    },
    "indicators": {
      "max_pain": 250.0,
      "call_wall": 280.0,
      "put_wall": 250.0,
      "zero_gamma": 234.46
    },
    "gex_chart_data": [
      {
        "strike": 205.0,
        "net_gex": -42785.97
      },
      {
        "strike": 210.0,
        "net_gex": -282860.07
      },
      {
        "strike": 215.0,
        "net_gex": -243612.66
      },
      {
        "strike": 220.0,
        "net_gex": -438054.18
      },
      {
        "strike": 225.0,
        "net_gex": -423956.49
      },
      {
        "strike": 230.0,
        "net_gex": -2757757.47
      },
      {
        "strike": 235.0,
        "net_gex": -1754056.9
      },
      {
        "strike": 240.0,
        "net_gex": 3547555.95
      },
      {
        "strike": 245.0,
        "net_gex": -2222425.42
      },
      {
        "strike": 250.0,
        "net_gex": -3904867.94
      },
      {
        "strike": 255.0,
        "net_gex": 1341502.51
      },
      {
        "strike": 260.0,
        "net_gex": -666298.21
      },
      {
        "strike": 265.0,
        "net_gex": 1452675.87
      },
      {
        "strike": 270.0,
        "net_gex": 3935242.58
      },
      {
        "strike": 275.0,
        "net_gex": 6550010.35
      },
      {
        "strike": 280.0,
        "net_gex": 8018014.83
      },
      {
        "strike": 285.0,
        "net_gex": 9644738.43
      },
      {
        "strike": 290.0,
        "net_gex": 5431938.46
      },
      {
        "strike": 295.0,
        "net_gex": 4493707.95
      },
      {
        "strike": 300.0,
        "net_gex": 5689110.15
      },
      {
        "strike": 305.0,
        "net_gex": 1701706.96
      },
      {
        "strike": 310.0,
        "net_gex": 3185152.44
      },
      {
        "strike": 315.0,
        "net_gex": 418193.17
      },
      {
        "strike": 320.0,
        "net_gex": 1394675.4
      },
      {
        "strike": 325.0,
        "net_gex": 298410.95
      },
      {
        "strike": 330.0,
        "net_gex": 560955.49
      },
      {
        "strike": 335.0,
        "net_gex": 272919.26
      },
      {
        "strike": 340.0,
        "net_gex": 222954.76
      }
    ]
  },
  "MSFT": {
    "metadata": {
      "ticker": "MSFT",
      "spot_price": 419.76,
      "expiration_date": "Historical Aggregated (2026-04-20)",
      "updated_at": "2026-04-21 12:01:04"
    },
    "indicators": {
      "max_pain": 400.0,
      "call_wall": 445.0,
      "put_wall": 400.0,
      "zero_gamma": 356.48
    },
    "gex_chart_data": [
      {
        "strike": 315.0,
        "net_gex": -25167.59
      },
      {
        "strike": 320.0,
        "net_gex": -129057.76
      },
      {
        "strike": 325.0,
        "net_gex": -103688.37
      },
      {
        "strike": 330.0,
        "net_gex": -264336.78
      },
      {
        "strike": 335.0,
        "net_gex": -10460.64
      },
      {
        "strike": 340.0,
        "net_gex": -330196.52
      },
      {
        "strike": 345.0,
        "net_gex": -247424.56
      },
      {
        "strike": 350.0,
        "net_gex": -720511.41
      },
      {
        "strike": 355.0,
        "net_gex": -283478.35
      },
      {
        "strike": 360.0,
        "net_gex": -667466.55
      },
      {
        "strike": 365.0,
        "net_gex": -258715.83
      },
      {
        "strike": 370.0,
        "net_gex": -1295234.32
      },
      {
        "strike": 375.0,
        "net_gex": -217790.88
      },
      {
        "strike": 380.0,
        "net_gex": -1009691.95
      },
      {
        "strike": 385.0,
        "net_gex": 398040.26
      },
      {
        "strike": 390.0,
        "net_gex": -795032.25
      },
      {
        "strike": 395.0,
        "net_gex": 51106.13
      },
      {
        "strike": 400.0,
        "net_gex": 1647909.15
      },
      {
        "strike": 405.0,
        "net_gex": -91446.86
      },
      {
        "strike": 410.0,
        "net_gex": 1505066.63
      },
      {
        "strike": 415.0,
        "net_gex": 1797963.86
      },
      {
        "strike": 420.0,
        "net_gex": 1061366.82
      },
      {
        "strike": 425.0,
        "net_gex": 1570298.32
      },
      {
        "strike": 430.0,
        "net_gex": 2842139.18
      },
      {
        "strike": 435.0,
        "net_gex": 2167315.9
      },
      {
        "strike": 440.0,
        "net_gex": 3003766.47
      },
      {
        "strike": 445.0,
        "net_gex": 21665534.87
      },
      {
        "strike": 450.0,
        "net_gex": 3254036.02
      },
      {
        "strike": 455.0,
        "net_gex": 454569.41
      },
      {
        "strike": 460.0,
        "net_gex": 2014684.39
      },
      {
        "strike": 465.0,
        "net_gex": 1105167.92
      },
      {
        "strike": 470.0,
        "net_gex": 1396399.04
      },
      {
        "strike": 475.0,
        "net_gex": 4728432.49
      },
      {
        "strike": 480.0,
        "net_gex": 1215728.33
      },
      {
        "strike": 485.0,
        "net_gex": 146428.89
      },
      {
        "strike": 490.0,
        "net_gex": 985593.04
      },
      {
        "strike": 495.0,
        "net_gex": 85436.39
      },
      {
        "strike": 500.0,
        "net_gex": 1345820.59
      },
      {
        "strike": 505.0,
        "net_gex": 85337.71
      },
      {
        "strike": 510.0,
        "net_gex": 285494.87
      },
      {
        "strike": 515.0,
        "net_gex": 38594.08
      },
      {
        "strike": 520.0,
        "net_gex": 238288.45
      }
    ]
  },
  "AMZN": {
    "metadata": {
      "ticker": "AMZN",
      "spot_price": 255.51,
      "expiration_date": "Historical Aggregated (2026-04-20)",
      "updated_at": "2026-04-21 12:01:07"
    },
    "indicators": {
      "max_pain": 210.0,
      "call_wall": 260.0,
      "put_wall": 235.0,
      "zero_gamma": 197.82
    },
    "gex_chart_data": [
      {
        "strike": 195.0,
        "net_gex": -417519.08
      },
      {
        "strike": 200.0,
        "net_gex": -274041.09
      },
      {
        "strike": 205.0,
        "net_gex": -197455.01
      },
      {
        "strike": 210.0,
        "net_gex": 524418.64
      },
      {
        "strike": 215.0,
        "net_gex": -101930.47
      },
      {
        "strike": 220.0,
        "net_gex": 520147.5
      },
      {
        "strike": 225.0,
        "net_gex": 847250.34
      },
      {
        "strike": 230.0,
        "net_gex": 1352619.23
      },
      {
        "strike": 235.0,
        "net_gex": 1259294.04
      },
      {
        "strike": 240.0,
        "net_gex": 3222894.77
      },
      {
        "strike": 245.0,
        "net_gex": 6360462.41
      },
      {
        "strike": 250.0,
        "net_gex": 9813488.22
      },
      {
        "strike": 255.0,
        "net_gex": 5723879.5
      },
      {
        "strike": 260.0,
        "net_gex": 13877765.17
      },
      {
        "strike": 265.0,
        "net_gex": 3401446.43
      },
      {
        "strike": 270.0,
        "net_gex": 4538652.84
      },
      {
        "strike": 275.0,
        "net_gex": 4610007.47
      },
      {
        "strike": 280.0,
        "net_gex": 4353352.4
      },
      {
        "strike": 285.0,
        "net_gex": 2057084.21
      },
      {
        "strike": 290.0,
        "net_gex": 1342489.41
      },
      {
        "strike": 295.0,
        "net_gex": 667687.39
      },
      {
        "strike": 300.0,
        "net_gex": 1187893.06
      },
      {
        "strike": 305.0,
        "net_gex": 273309.44
      },
      {
        "strike": 310.0,
        "net_gex": 711531.2
      },
      {
        "strike": 315.0,
        "net_gex": 144143.22
      }
    ]
  },
  "META": {
    "metadata": {
      "ticker": "META",
      "spot_price": 675.24,
      "expiration_date": "Historical Aggregated (2026-04-20)",
      "updated_at": "2026-04-21 12:01:09"
    },
    "indicators": {
      "max_pain": 600.0,
      "call_wall": 720.0,
      "put_wall": 600.0,
      "zero_gamma": 577.76
    },
    "gex_chart_data": [
      {
        "strike": 510.0,
        "net_gex": -71152.85
      },
      {
        "strike": 515.0,
        "net_gex": -9764.5
      },
      {
        "strike": 520.0,
        "net_gex": -158411.22
      },
      {
        "strike": 525.0,
        "net_gex": -41843.47
      },
      {
        "strike": 530.0,
        "net_gex": -100692.98
      },
      {
        "strike": 535.0,
        "net_gex": -17899.49
      },
      {
        "strike": 540.0,
        "net_gex": -77224.51
      },
      {
        "strike": 545.0,
        "net_gex": -28303.56
      },
      {
        "strike": 550.0,
        "net_gex": -221468.52
      },
      {
        "strike": 555.0,
        "net_gex": -36112.64
      },
      {
        "strike": 560.0,
        "net_gex": -106351.47
      },
      {
        "strike": 565.0,
        "net_gex": -71731.8
      },
      {
        "strike": 570.0,
        "net_gex": -328708.59
      },
      {
        "strike": 575.0,
        "net_gex": -105515.01
      },
      {
        "strike": 580.0,
        "net_gex": -224628.37
      },
      {
        "strike": 585.0,
        "net_gex": -48864.98
      },
      {
        "strike": 590.0,
        "net_gex": -171640.46
      },
      {
        "strike": 595.0,
        "net_gex": -179496.39
      },
      {
        "strike": 600.0,
        "net_gex": 257929.42
      },
      {
        "strike": 605.0,
        "net_gex": 145645.36
      },
      {
        "strike": 610.0,
        "net_gex": -112675.45
      },
      {
        "strike": 615.0,
        "net_gex": -56323.8
      },
      {
        "strike": 620.0,
        "net_gex": -129151.48
      },
      {
        "strike": 625.0,
        "net_gex": 173175.89
      },
      {
        "strike": 630.0,
        "net_gex": 5373.28
      },
      {
        "strike": 635.0,
        "net_gex": 81485.84
      },
      {
        "strike": 640.0,
        "net_gex": 62523.89
      },
      {
        "strike": 645.0,
        "net_gex": 82967.75
      },
      {
        "strike": 650.0,
        "net_gex": 924863.81
      },
      {
        "strike": 655.0,
        "net_gex": 158355.52
      },
      {
        "strike": 660.0,
        "net_gex": 500810.61
      },
      {
        "strike": 665.0,
        "net_gex": 357181.39
      },
      {
        "strike": 670.0,
        "net_gex": 298650.31
      },
      {
        "strike": 675.0,
        "net_gex": 467437.72
      },
      {
        "strike": 680.0,
        "net_gex": 2627181.82
      },
      {
        "strike": 685.0,
        "net_gex": 255987.5
      },
      {
        "strike": 690.0,
        "net_gex": 434705.84
      },
      {
        "strike": 695.0,
        "net_gex": 247411.07
      },
      {
        "strike": 700.0,
        "net_gex": 2292833.04
      },
      {
        "strike": 705.0,
        "net_gex": 531457.26
      },
      {
        "strike": 710.0,
        "net_gex": 1298992.0
      },
      {
        "strike": 715.0,
        "net_gex": 369283.73
      },
      {
        "strike": 720.0,
        "net_gex": 3310558.36
      },
      {
        "strike": 725.0,
        "net_gex": 231259.71
      },
      {
        "strike": 730.0,
        "net_gex": 1145176.41
      },
      {
        "strike": 735.0,
        "net_gex": 93532.87
      },
      {
        "strike": 740.0,
        "net_gex": 457830.77
      },
      {
        "strike": 745.0,
        "net_gex": 255927.93
      },
      {
        "strike": 750.0,
        "net_gex": 950456.28
      },
      {
        "strike": 755.0,
        "net_gex": 97998.08
      },
      {
        "strike": 760.0,
        "net_gex": 341548.65
      },
      {
        "strike": 765.0,
        "net_gex": 270199.67
      },
      {
        "strike": 770.0,
        "net_gex": 730582.29
      },
      {
        "strike": 775.0,
        "net_gex": 325720.39
      },
      {
        "strike": 780.0,
        "net_gex": 553530.68
      },
      {
        "strike": 785.0,
        "net_gex": 82103.34
      },
      {
        "strike": 790.0,
        "net_gex": 181230.11
      },
      {
        "strike": 795.0,
        "net_gex": 23483.66
      },
      {
        "strike": 800.0,
        "net_gex": 1553501.44
      },
      {
        "strike": 805.0,
        "net_gex": 40268.35
      },
      {
        "strike": 810.0,
        "net_gex": 223089.26
      },
      {
        "strike": 815.0,
        "net_gex": 9929.86
      },
      {
        "strike": 820.0,
        "net_gex": 82226.78
      },
      {
        "strike": 825.0,
        "net_gex": 40828.32
      },
      {
        "strike": 830.0,
        "net_gex": 69852.42
      },
      {
        "strike": 835.0,
        "net_gex": 5519.35
      },
      {
        "strike": 840.0,
        "net_gex": 24025.28
      }
    ]
  },
  "GOOGL": {
    "metadata": {
      "ticker": "GOOGL",
      "spot_price": 338.74,
      "expiration_date": "Historical Aggregated (2026-04-20)",
      "updated_at": "2026-04-21 12:01:12"
    },
    "indicators": {
      "max_pain": 300.0,
      "call_wall": 355.0,
      "put_wall": 300.0,
      "zero_gamma": 275.81
    },
    "gex_chart_data": [
      {
        "strike": 255.0,
        "net_gex": -86007.89
      },
      {
        "strike": 260.0,
        "net_gex": -172216.59
      },
      {
        "strike": 265.0,
        "net_gex": -51769.95
      },
      {
        "strike": 270.0,
        "net_gex": -357864.46
      },
      {
        "strike": 275.0,
        "net_gex": -263769.61
      },
      {
        "strike": 280.0,
        "net_gex": -590452.45
      },
      {
        "strike": 285.0,
        "net_gex": -420345.99
      },
      {
        "strike": 290.0,
        "net_gex": -575089.49
      },
      {
        "strike": 295.0,
        "net_gex": -159970.85
      },
      {
        "strike": 300.0,
        "net_gex": -780180.39
      },
      {
        "strike": 305.0,
        "net_gex": -335311.1
      },
      {
        "strike": 310.0,
        "net_gex": 1717796.6
      },
      {
        "strike": 315.0,
        "net_gex": 1545599.57
      },
      {
        "strike": 320.0,
        "net_gex": 1685564.76
      },
      {
        "strike": 325.0,
        "net_gex": 959868.38
      },
      {
        "strike": 330.0,
        "net_gex": 3128308.98
      },
      {
        "strike": 335.0,
        "net_gex": 7471053.23
      },
      {
        "strike": 340.0,
        "net_gex": 1968444.9
      },
      {
        "strike": 345.0,
        "net_gex": 2899433.02
      },
      {
        "strike": 350.0,
        "net_gex": 2079847.23
      },
      {
        "strike": 355.0,
        "net_gex": 14790559.4
      },
      {
        "strike": 360.0,
        "net_gex": 2722936.4
      },
      {
        "strike": 365.0,
        "net_gex": 803552.81
      },
      {
        "strike": 370.0,
        "net_gex": 2414596.33
      },
      {
        "strike": 375.0,
        "net_gex": 3624962.31
      },
      {
        "strike": 380.0,
        "net_gex": 642304.25
      },
      {
        "strike": 385.0,
        "net_gex": 278530.64
      },
      {
        "strike": 390.0,
        "net_gex": 504432.74
      },
      {
        "strike": 395.0,
        "net_gex": 116132.78
      },
      {
        "strike": 400.0,
        "net_gex": 327853.78
      },
      {
        "strike": 405.0,
        "net_gex": 33958.33
      },
      {
        "strike": 410.0,
        "net_gex": 108734.3
      },
      {
        "strike": 415.0,
        "net_gex": 13656.91
      },
      {
        "strike": 420.0,
        "net_gex": 130466.24
      }
    ]
  },
  "AMD": {
    "metadata": {
      "ticker": "AMD",
      "spot_price": 277.27,
      "expiration_date": "Historical Aggregated (2026-04-20)",
      "updated_at": "2026-04-21 12:01:14"
    },
    "indicators": {
      "max_pain": 210.0,
      "call_wall": 280.0,
      "put_wall": 250.0,
      "zero_gamma": 211.54
    },
    "gex_chart_data": [
      {
        "strike": 210.0,
        "net_gex": 2612.73
      },
      {
        "strike": 220.0,
        "net_gex": 145087.66
      },
      {
        "strike": 230.0,
        "net_gex": 143201.84
      },
      {
        "strike": 240.0,
        "net_gex": 308249.41
      },
      {
        "strike": 250.0,
        "net_gex": 1279408.35
      },
      {
        "strike": 260.0,
        "net_gex": 1732123.66
      },
      {
        "strike": 270.0,
        "net_gex": 1330227.09
      },
      {
        "strike": 280.0,
        "net_gex": 2792861.26
      },
      {
        "strike": 290.0,
        "net_gex": 1829595.28
      },
      {
        "strike": 300.0,
        "net_gex": 2906133.14
      },
      {
        "strike": 310.0,
        "net_gex": 1123850.58
      },
      {
        "strike": 320.0,
        "net_gex": 367056.73
      },
      {
        "strike": 330.0,
        "net_gex": 403204.51
      },
      {
        "strike": 340.0,
        "net_gex": 263011.99
      }
    ]
  },
  "TSM": {
    "metadata": {
      "ticker": "TSM",
      "spot_price": 368.71,
      "expiration_date": "Historical Aggregated (2026-04-20)",
      "updated_at": "2026-04-21 12:01:16"
    },
    "indicators": {
      "max_pain": 340.0,
      "call_wall": 350.0,
      "put_wall": 330.0,
      "zero_gamma": 366.98
    },
    "gex_chart_data": [
      {
        "strike": 280.0,
        "net_gex": -142547.81
      },
      {
        "strike": 290.0,
        "net_gex": -228647.2
      },
      {
        "strike": 300.0,
        "net_gex": -450644.17
      },
      {
        "strike": 310.0,
        "net_gex": -197249.41
      },
      {
        "strike": 320.0,
        "net_gex": -1247763.39
      },
      {
        "strike": 330.0,
        "net_gex": -3699511.22
      },
      {
        "strike": 340.0,
        "net_gex": -2872612.4
      },
      {
        "strike": 350.0,
        "net_gex": 692659.9
      },
      {
        "strike": 360.0,
        "net_gex": 1088156.25
      },
      {
        "strike": 370.0,
        "net_gex": 962381.69
      },
      {
        "strike": 380.0,
        "net_gex": 1171216.99
      },
      {
        "strike": 390.0,
        "net_gex": 1572498.71
      },
      {
        "strike": 400.0,
        "net_gex": 1720325.46
      },
      {
        "strike": 410.0,
        "net_gex": 694948.58
      },
      {
        "strike": 420.0,
        "net_gex": 658299.26
      },
      {
        "strike": 430.0,
        "net_gex": 273642.82
      },
      {
        "strike": 440.0,
        "net_gex": 323128.22
      },
      {
        "strike": 450.0,
        "net_gex": 125492.11
      },
      {
        "strike": 460.0,
        "net_gex": 46889.02
      }
    ]
  },
  "SMCI": {
    "metadata": {
      "ticker": "SMCI",
      "spot_price": 29.26,
      "expiration_date": "Historical Aggregated (2026-04-20)",
      "updated_at": "2026-04-21 12:01:18"
    },
    "indicators": {
      "max_pain": 30.0,
      "call_wall": 32.0,
      "put_wall": 28.0,
      "zero_gamma": 24.49
    },
    "gex_chart_data": [
      {
        "strike": 22.0,
        "net_gex": -21991.99
      },
      {
        "strike": 23.0,
        "net_gex": -6989.47
      },
      {
        "strike": 24.0,
        "net_gex": 30648.82
      },
      {
        "strike": 25.0,
        "net_gex": -154112.95
      },
      {
        "strike": 26.0,
        "net_gex": 451378.0
      },
      {
        "strike": 27.0,
        "net_gex": 516458.43
      },
      {
        "strike": 28.0,
        "net_gex": -1171790.33
      },
      {
        "strike": 29.0,
        "net_gex": 285032.89
      },
      {
        "strike": 30.0,
        "net_gex": 5313961.51
      },
      {
        "strike": 31.0,
        "net_gex": 894556.77
      },
      {
        "strike": 32.0,
        "net_gex": 10911234.55
      },
      {
        "strike": 33.0,
        "net_gex": 422376.14
      },
      {
        "strike": 34.0,
        "net_gex": 149350.61
      },
      {
        "strike": 35.0,
        "net_gex": 756107.52
      },
      {
        "strike": 36.0,
        "net_gex": 46081.37
      }
    ]
  },
  "MSTR": {
    "metadata": {
      "ticker": "MSTR",
      "spot_price": 173.71,
      "expiration_date": "Historical Aggregated (2026-04-20)",
      "updated_at": "2026-04-21 12:01:26"
    },
    "indicators": {
      "max_pain": 140.0,
      "call_wall": 170.0,
      "put_wall": 180.0,
      "zero_gamma": 140.0
    },
    "gex_chart_data": [
      {
        "strike": 135.0,
        "net_gex": -15495.25
      },
      {
        "strike": 140.0,
        "net_gex": 2283272.24
      },
      {
        "strike": 145.0,
        "net_gex": -166234.63
      },
      {
        "strike": 150.0,
        "net_gex": 515267.95
      },
      {
        "strike": 155.0,
        "net_gex": 151110.53
      },
      {
        "strike": 160.0,
        "net_gex": 1489577.94
      },
      {
        "strike": 165.0,
        "net_gex": 855272.37
      },
      {
        "strike": 170.0,
        "net_gex": 1945560.03
      },
      {
        "strike": 175.0,
        "net_gex": 967661.81
      },
      {
        "strike": 180.0,
        "net_gex": 1165817.64
      },
      {
        "strike": 185.0,
        "net_gex": 846554.74
      },
      {
        "strike": 190.0,
        "net_gex": 151738.84
      },
      {
        "strike": 195.0,
        "net_gex": 356326.48
      },
      {
        "strike": 200.0,
        "net_gex": 1830379.51
      },
      {
        "strike": 205.0,
        "net_gex": -50902.9
      },
      {
        "strike": 210.0,
        "net_gex": 48090.49
      },
      {
        "strike": 215.0,
        "net_gex": 40185.58
      }
    ]
  },
  "NFLX": {
    "metadata": {
      "ticker": "NFLX",
      "spot_price": 95.12,
      "expiration_date": "Historical Aggregated (2026-04-20)",
      "updated_at": "2026-04-21 12:01:29"
    },
    "indicators": {
      "max_pain": 94.0,
      "call_wall": 105.0,
      "put_wall": 93.0,
      "zero_gamma": 84.35
    },
    "gex_chart_data": [
      {
        "strike": 72.0,
        "net_gex": -22390.58
      },
      {
        "strike": 73.0,
        "net_gex": -314015.2
      },
      {
        "strike": 74.0,
        "net_gex": -27415.49
      },
      {
        "strike": 75.0,
        "net_gex": -340198.06
      },
      {
        "strike": 76.0,
        "net_gex": -124662.22
      },
      {
        "strike": 77.0,
        "net_gex": -230844.31
      },
      {
        "strike": 78.0,
        "net_gex": -711437.55
      },
      {
        "strike": 79.0,
        "net_gex": -67556.18
      },
      {
        "strike": 80.0,
        "net_gex": -1294640.88
      },
      {
        "strike": 81.0,
        "net_gex": -68908.36
      },
      {
        "strike": 82.0,
        "net_gex": -375432.94
      },
      {
        "strike": 83.0,
        "net_gex": -83745.01
      },
      {
        "strike": 84.0,
        "net_gex": 84605.34
      },
      {
        "strike": 85.0,
        "net_gex": 226851.1
      },
      {
        "strike": 86.0,
        "net_gex": -199774.42
      },
      {
        "strike": 87.0,
        "net_gex": -168179.99
      },
      {
        "strike": 88.0,
        "net_gex": -481666.99
      },
      {
        "strike": 89.0,
        "net_gex": -191943.6
      },
      {
        "strike": 90.0,
        "net_gex": 6501800.79
      },
      {
        "strike": 91.0,
        "net_gex": -693321.56
      },
      {
        "strike": 92.0,
        "net_gex": -1198628.49
      },
      {
        "strike": 93.0,
        "net_gex": -3530899.05
      },
      {
        "strike": 94.0,
        "net_gex": -160206.24
      },
      {
        "strike": 95.0,
        "net_gex": 1595329.23
      },
      {
        "strike": 96.0,
        "net_gex": -337267.59
      },
      {
        "strike": 97.0,
        "net_gex": -453861.39
      },
      {
        "strike": 98.0,
        "net_gex": 1792745.53
      },
      {
        "strike": 99.0,
        "net_gex": -4851.66
      },
      {
        "strike": 100.0,
        "net_gex": 6736885.1
      },
      {
        "strike": 101.0,
        "net_gex": 400734.15
      },
      {
        "strike": 102.0,
        "net_gex": 723853.48
      },
      {
        "strike": 103.0,
        "net_gex": 875880.25
      },
      {
        "strike": 104.0,
        "net_gex": -1602259.97
      },
      {
        "strike": 105.0,
        "net_gex": 11038968.04
      },
      {
        "strike": 106.0,
        "net_gex": 769446.15
      },
      {
        "strike": 107.0,
        "net_gex": 244950.53
      },
      {
        "strike": 108.0,
        "net_gex": -681249.82
      },
      {
        "strike": 109.0,
        "net_gex": 276269.28
      },
      {
        "strike": 110.0,
        "net_gex": 2750333.79
      },
      {
        "strike": 111.0,
        "net_gex": 456067.9
      },
      {
        "strike": 112.0,
        "net_gex": 818667.85
      },
      {
        "strike": 114.0,
        "net_gex": 670313.62
      },
      {
        "strike": 115.0,
        "net_gex": 3479284.26
      },
      {
        "strike": 116.0,
        "net_gex": 155321.65
      },
      {
        "strike": 118.0,
        "net_gex": 314218.76
      }
    ]
  },
  "JPM": {
    "metadata": {
      "ticker": "JPM",
      "spot_price": 317.68,
      "expiration_date": "Historical Aggregated (2026-04-20)",
      "updated_at": "2026-04-21 12:01:31"
    },
    "indicators": {
      "max_pain": 300.0,
      "call_wall": 320.0,
      "put_wall": 280.0,
      "zero_gamma": 285.89
    },
    "gex_chart_data": [
      {
        "strike": 240.0,
        "net_gex": -27485.27
      },
      {
        "strike": 245.0,
        "net_gex": -25383.01
      },
      {
        "strike": 250.0,
        "net_gex": -441164.94
      },
      {
        "strike": 255.0,
        "net_gex": -96882.87
      },
      {
        "strike": 260.0,
        "net_gex": -141553.44
      },
      {
        "strike": 265.0,
        "net_gex": -125994.58
      },
      {
        "strike": 270.0,
        "net_gex": -303363.98
      },
      {
        "strike": 275.0,
        "net_gex": -190220.85
      },
      {
        "strike": 280.0,
        "net_gex": -691039.73
      },
      {
        "strike": 285.0,
        "net_gex": -282943.76
      },
      {
        "strike": 290.0,
        "net_gex": -12923.68
      },
      {
        "strike": 295.0,
        "net_gex": -46476.77
      },
      {
        "strike": 300.0,
        "net_gex": 168609.89
      },
      {
        "strike": 305.0,
        "net_gex": 42471.25
      },
      {
        "strike": 310.0,
        "net_gex": 839099.07
      },
      {
        "strike": 315.0,
        "net_gex": 1240115.99
      },
      {
        "strike": 320.0,
        "net_gex": 1638543.62
      },
      {
        "strike": 325.0,
        "net_gex": 851677.41
      },
      {
        "strike": 330.0,
        "net_gex": 1186210.8
      },
      {
        "strike": 335.0,
        "net_gex": 578837.92
      },
      {
        "strike": 340.0,
        "net_gex": 817583.42
      },
      {
        "strike": 345.0,
        "net_gex": 542727.37
      },
      {
        "strike": 350.0,
        "net_gex": 280966.58
      },
      {
        "strike": 355.0,
        "net_gex": 20860.86
      },
      {
        "strike": 360.0,
        "net_gex": 159660.51
      },
      {
        "strike": 365.0,
        "net_gex": 13232.38
      },
      {
        "strike": 370.0,
        "net_gex": 156564.79
      },
      {
        "strike": 375.0,
        "net_gex": 12282.82
      },
      {
        "strike": 380.0,
        "net_gex": 55623.21
      },
      {
        "strike": 390.0,
        "net_gex": 12047.04
      },
      {
        "strike": 395.0,
        "net_gex": 929.8
      }
    ]
  },
  "V": {
    "metadata": {
      "ticker": "V",
      "spot_price": 314.85,
      "expiration_date": "Historical Aggregated (2026-04-20)",
      "updated_at": "2026-04-21 12:01:33"
    },
    "indicators": {
      "max_pain": 315.0,
      "call_wall": 340.0,
      "put_wall": 300.0,
      "zero_gamma": 289.17
    },
    "gex_chart_data": [
      {
        "strike": 240.0,
        "net_gex": -4408.79
      },
      {
        "strike": 245.0,
        "net_gex": -3488.29
      },
      {
        "strike": 250.0,
        "net_gex": -12355.76
      },
      {
        "strike": 255.0,
        "net_gex": -14865.94
      },
      {
        "strike": 260.0,
        "net_gex": -53432.43
      },
      {
        "strike": 265.0,
        "net_gex": -91126.5
      },
      {
        "strike": 270.0,
        "net_gex": -137545.74
      },
      {
        "strike": 275.0,
        "net_gex": -422864.72
      },
      {
        "strike": 280.0,
        "net_gex": -451820.92
      },
      {
        "strike": 285.0,
        "net_gex": -137187.31
      },
      {
        "strike": 290.0,
        "net_gex": -300781.38
      },
      {
        "strike": 295.0,
        "net_gex": -214852.59
      },
      {
        "strike": 300.0,
        "net_gex": -434424.54
      },
      {
        "strike": 305.0,
        "net_gex": -138378.3
      },
      {
        "strike": 310.0,
        "net_gex": -154759.2
      },
      {
        "strike": 315.0,
        "net_gex": -142975.11
      },
      {
        "strike": 320.0,
        "net_gex": 565499.06
      },
      {
        "strike": 325.0,
        "net_gex": 471028.69
      },
      {
        "strike": 330.0,
        "net_gex": 348972.93
      },
      {
        "strike": 335.0,
        "net_gex": 270659.67
      },
      {
        "strike": 340.0,
        "net_gex": 3214947.21
      },
      {
        "strike": 345.0,
        "net_gex": 458387.11
      },
      {
        "strike": 350.0,
        "net_gex": 238371.54
      },
      {
        "strike": 355.0,
        "net_gex": 454518.62
      },
      {
        "strike": 360.0,
        "net_gex": 289927.48
      },
      {
        "strike": 365.0,
        "net_gex": 47839.87
      },
      {
        "strike": 370.0,
        "net_gex": 119768.63
      },
      {
        "strike": 375.0,
        "net_gex": 36942.62
      },
      {
        "strike": 380.0,
        "net_gex": 39738.71
      },
      {
        "strike": 385.0,
        "net_gex": 81289.51
      },
      {
        "strike": 390.0,
        "net_gex": 58224.39
      }
    ]
  }
}